README.md
setup.cfg
setup.py
Flask_CloudFlare.egg-info/PKG-INFO
Flask_CloudFlare.egg-info/SOURCES.txt
Flask_CloudFlare.egg-info/dependency_links.txt
Flask_CloudFlare.egg-info/requires.txt
Flask_CloudFlare.egg-info/top_level.txt
flask_cloudflare/__init__.py