Metadata-Version: 1.0
Name: Flask-CloudFlare
Version: 0.7
Summary: A Flask extension that wraps pycflare to provide python bindings for CloudFlare's API.
Home-page: https://github.com/BillSchumacher/Flask-CloudFlare
Author: Bill Schumacher
Author-email: williamschumacher@gmail.com
License: BSD 0-Clause
Keywords: cloudflare workers kv flask
Platform: UNKNOWN
